LICENSE
README.md
setup.py
rytuo_package/__init__.py
rytuo_package/fast_hist.py
rytuo_package.egg-info/PKG-INFO
rytuo_package.egg-info/SOURCES.txt
rytuo_package.egg-info/dependency_links.txt
rytuo_package.egg-info/requires.txt
rytuo_package.egg-info/top_level.txt