Metadata-Version: 2.1
Name: rytuo-package
Version: 0.1.0
Summary: An example Python package
Home-page: https://github.com/Rytuo/rytuo_package
Author: Aleksandr Popov
Author-email: popov.aleksandt.v@yandex.ru
License: MIT
Platform: UNKNOWN
Classifier: Development Status :: 1 - Planning
Classifier: Operating System :: POSIX :: Linux
Classifier: Programming Language :: Python :: 3
License-File: LICENSE
